DESCRIPTION.rst
MANIFEST.in
README.rst
setup.cfg
setup.py
doc/install_mpc55xx_bam_01.html
doc/install_mpc55xx_bam_01.xml
src/mpc55xx/__init__.py
src/mpc55xx/mpc55xx_bam_01.py
src/mpc55xx_bam_loader_g1.egg-info/PKG-INFO
src/mpc55xx_bam_loader_g1.egg-info/SOURCES.txt
src/mpc55xx_bam_loader_g1.egg-info/dependency_links.txt
src/mpc55xx_bam_loader_g1.egg-info/entry_points.txt
src/mpc55xx_bam_loader_g1.egg-info/requires.txt
src/mpc55xx_bam_loader_g1.egg-info/top_level.txt