Metadata-Version: 1.1
Name: mpc55xx-bam-loader-g1
Version: 1.0.1
Summary: Upload binaries to Freescale MPC55xx or MPC56xx with the BAM serial protocol
Home-page: https://github.com/KoblerSystems/mpc55xx-bam-loader-01
Author: Jan Kobler, Kobler System GmbH
Author-email: eng1@koblersystems.de
License: MIT
Keywords: Freescale MPC55xx,Freescale MPC56xx,bootloader,Boot Assist Module (BAM)
Platform: UNKNOWN
Classifier: Development Status :: 4 - Beta
Classifier: Operating System :: OS Independent
Classifier: Intended Audience :: Developers
Classifier: Topic :: Software Development :: Embedded Systems
Classifier: License :: OSI Approved :: MIT License
Classifier: Programming Language :: Python :: 3
Classifier: Programming Language :: Python :: 3.2
Classifier: Programming Language :: Python :: 3.3
Classifier: Programming Language :: Python :: 3.4
Classifier: Programming Language :: Python :: 3 :: Only
